CustomCrypto.py
LICENSE.txt
MANIFEST.in
README.md
setup.py
CustomCrypto.egg-info/PKG-INFO
CustomCrypto.egg-info/SOURCES.txt
CustomCrypto.egg-info/dependency_links.txt
CustomCrypto.egg-info/top_level.txt