Metadata-Version: 2.1
Name: CustomCrypto
Version: 0.0.2
Summary:  This package implements tools to build your custom cipher. 
Home-page: https://github.com/mauricelambert/CustomCrypto
Author: Maurice Lambert
Author-email: mauricelambert434@gmail.com
Maintainer: Maurice Lambert
Maintainer-email: mauricelambert434@gmail.com
License: GPL-3.0 License
Project-URL: Documentation, https://mauricelambert.github.io/info/python/security/CustomCrypto.html
Keywords: Cryptography,Custom
Platform: Windows
Platform: Linux
Platform: MacOS
Classifier: Programming Language :: Python
Classifier: Development Status :: 5 - Production/Stable
Classifier: Topic :: Security :: Cryptography
Classifier: Natural Language :: English
Classifier: Programming Language :: Python :: 3.9
Classifier: Operating System :: POSIX :: Linux
Classifier: Operating System :: Microsoft :: Windows
Classifier: Operating System :: MacOS
Requires-Python: >=3.6
License-File: LICENSE.txt
